mk2lib/__init__.py
mk2lib/cards.py
mk2lib/const.py
mk2lib/dice.py
mk2lib/effects.py
mk2lib/events.py
mk2lib/game.py
mk2lib/mk2deck.py
mk2lib/player.py
mk2lib-1.1.2.dist-info/METADATA
mk2lib-1.1.2.dist-info/WHEEL
mk2lib-1.1.2.dist-info/licenses/LICENSE
mk2lib-1.1.2.dist-info/RECORD
