Metadata-Version: 2.4
Name: mk2lib
Version: 1.1.2
Summary: Machi Koro 2 Game Engine
Project-URL: Homepage, https://github.com/ostrosablin/mk2lib
Project-URL: Documentation, https://github.com/ostrosablin/mk2lib/tree/master/docs
Project-URL: Bug Tracker, https://github.com/ostrosablin/mk2lib/issues
Project-URL: Source Code, https://github.com/ostrosablin/mk2lib
Author-email: Vitaly Ostrosablin <tmp6154@yandex.ru>
License-Expression: GPL-3.0-only
License-File: LICENSE
Keywords: boardgame,engine,game,python
Classifier: Development Status :: 5 - Production/Stable
Classifier: Intended Audience :: Developers
Classifier: License :: OSI Approved :: GNU General Public License v3 (GPLv3)
Classifier: Operating System :: OS Independent
Classifier: Programming Language :: Python
Classifier: Programming Language :: Python :: 3
Classifier: Programming Language :: Python :: 3.10
Classifier: Programming Language :: Python :: 3.11
Classifier: Programming Language :: Python :: 3.12
Classifier: Programming Language :: Python :: 3.13
Classifier: Programming Language :: Python :: 3.14
Classifier: Topic :: Games/Entertainment
Classifier: Topic :: Games/Entertainment :: Board Games
Classifier: Topic :: Games/Entertainment :: Simulation
Classifier: Topic :: Software Development :: Libraries :: Python Modules
Requires-Python: >=3.10
Provides-Extra: all
